twixtools/__init__.py
twixtools/geometry.py
twixtools/hdr_def.py
twixtools/helpers.py
twixtools/map_twix.py
twixtools/mdb.py
twixtools/mdh_def.py
twixtools/pmu.py
twixtools/quat.py
twixtools/recon_helpers.py
twixtools/seqdata.py
twixtools/twixprot.py
twixtools/twixtools.py
twixtools/contrib/LICENSE
twixtools/contrib/cfl.py
twixtools/utils/__init__.py
twixtools/utils/convert_to_cfl.py
twixtools/utils/datmeta2json.py
twixtools/utils/rotate_3Dcfl.py
twixtools/utils/twix_starttime.py
twixtools-0.24.dist-info/licenses/LICENSE
twixtools-0.24.dist-info/METADATA
twixtools-0.24.dist-info/WHEEL
twixtools-0.24.dist-info/entry_points.txt
twixtools-0.24.dist-info/top_level.txt
twixtools-0.24.dist-info/RECORD
