Metadata-Version: 2.4
Name: twixtools
Version: 0.24
Summary: file reader for Siemens twix(.dat)-files
Author-email: Philipp Ehses <philipp.ehses@dzne.de>
License: MIT License
Project-URL: Homepage, https://github.com/pehses/twixtools
Project-URL: Issues, https://github.com/pehses/twixtools/issues
Keywords: twix,siemens,mri
Classifier: Programming Language :: Python :: 3
Classifier: Operating System :: OS Independent
Requires-Python: <4,>=3.8
License-File: LICENSE
Requires-Dist: numpy
Requires-Dist: scipy
Requires-Dist: matplotlib
Requires-Dist: setuptools
Requires-Dist: tqdm
Provides-Extra: test
Requires-Dist: pytest; extra == "test"
Dynamic: license-file
